ofxstatement_revolut-2.0.4-py3.9-nspkg.pth
ofxstatement/plugins/revolut.py
ofxstatement_revolut-2.0.4.dist-info/LICENSE
ofxstatement_revolut-2.0.4.dist-info/METADATA
ofxstatement_revolut-2.0.4.dist-info/WHEEL
ofxstatement_revolut-2.0.4.dist-info/entry_points.txt
ofxstatement_revolut-2.0.4.dist-info/namespace_packages.txt
ofxstatement_revolut-2.0.4.dist-info/top_level.txt
ofxstatement_revolut-2.0.4.dist-info/zip-safe
ofxstatement_revolut-2.0.4.dist-info/RECORD
