Metadata-Version: 2.1
Name: ofxstatement-revolut
Version: 2.0.4
Summary: Bank statement parser for Revolut
Home-page: https://github.com/mlaitinen/ofxstatement-revolut
Author: Miku Laitinen
Author-email: miku@avoin.systems
License: GPLv3
Keywords: ofx,ofxstatement,banking,statement,revolut
Classifier: Development Status :: 4 - Beta
Classifier: Programming Language :: Python :: 3
Classifier: Natural Language :: English
Classifier: Topic :: Office/Business :: Financial :: Accounting
Classifier: Topic :: Utilities
Classifier: Environment :: Console
Classifier: Operating System :: OS Independent
Classifier: License :: OSI Approved :: GNU General Public License v3 (GPLv3)
License-File: LICENSE
Requires-Dist: ofxstatement >=0.7.2
Provides-Extra: test
Requires-Dist: pytest ; extra == 'test'
